EO/EO.py
EO/__init__.py
EOtool-0.0.2.dist-info/LICENSE
EOtool-0.0.2.dist-info/METADATA
EOtool-0.0.2.dist-info/WHEEL
EOtool-0.0.2.dist-info/top_level.txt
EOtool-0.0.2.dist-info/RECORD
